.gitignore
AUTHORS.rst
CHANGES.rst
LICENSE.txt
README.md
setup.py
tests/base_test.py
tests/requirements.txt
texim/__init__.py
texim/base.py
texim.egg-info/PKG-INFO
texim.egg-info/SOURCES.txt
texim.egg-info/dependency_links.txt
texim.egg-info/top_level.txt