Metadata-Version: 2.1
Name: texim
Version: 0.0.1
Summary: texim
Home-page: https://github.com/spenly/texim.git
Author: spenly
Author-email: i@spenly.com
License: UNKNOWN
Platform: UNKNOWN
Classifier: Programming Language :: Python :: 3
Classifier: License :: OSI Approved :: MIT License
Classifier: Operating System :: OS Independent
Requires-Python: >=3.5
